block2.cpython-39-x86_64-linux-gnu.so
pyblock2/ft_gfdmrg.py
pyblock2/dmrgscf.py
pyblock2/gsdmrg.py
pyblock2/ci.py
pyblock2/mp.py
pyblock2/gfdmrg.py
pyblock2/tools.py
pyblock2/sidmrg.py
pyblock2/chebydmrg.py
pyblock2/ft_dmrg.py
pyblock2/mrpt.py
pyblock2/__init__.py
pyblock2/ltdmrg.py
pyblock2/ft_chebydmrg.py
pyblock2/ft_tddmrg.py
pyblock2/ftdmrg.py
pyblock2/cc/eom_gccsd.py
pyblock2/cc/uccsd.py
pyblock2/cc/gccsdt.py
pyblock2/cc/rdm_uccsd.py
pyblock2/cc/rccsd.py
pyblock2/cc/lambda_rccsd.py
pyblock2/cc/rccsdt.py
pyblock2/cc/eom_rccsd.py
pyblock2/cc/gccsd.py
pyblock2/cc/rdm_gccsd.py
pyblock2/cc/rdm_rccsd.py
pyblock2/cc/lambda_gccsd.py
pyblock2/cc/eom_uccsd.py
pyblock2/cc/__init__.py
pyblock2/cc/lambda_uccsd.py
pyblock2/driver/readwfn.py
pyblock2/driver/core.py
pyblock2/driver/parser.py
pyblock2/driver/stopt.py
pyblock2/driver/__init__.py
pyblock2/driver/writewfn.py
pyblock2/algebra/core.py
pyblock2/algebra/hamil.py
pyblock2/algebra/io.py
pyblock2/algebra/__init__.py
pyblock2/algebra/pde.py
pyblock2/uc/ci.py
pyblock2/uc/mp.py
pyblock2/uc/__init__.py
pyblock2/icmr/eri_helper.py
pyblock2/icmr/icmrrept2_full.py
pyblock2/icmr/icnevpt2_ortho.py
pyblock2/icmr/icmrcisd_full.py
pyblock2/icmr/dmrg_helper.py
pyblock2/icmr/icnevpt2_full.py
pyblock2/icmr/icnevpt2.py
pyblock2/icmr/icmrrept2_ortho.py
pyblock2/icmr/scnevpt2.py
pyblock2/icmr/__init__.py
pyblock2/_pyscf/__init__.py
pyblock2/_pyscf/scf/init_guess.py
pyblock2/_pyscf/scf/smearing.py
pyblock2/_pyscf/scf/__init__.py
pyblock2/_pyscf/ao2mo/soc_integrals.py
pyblock2/_pyscf/ao2mo/__init__.py
pyblock2/_pyscf/ao2mo/integrals.py
pyblock2/_pyscf/mcscf/uno.py
pyblock2/_pyscf/mcscf/__init__.py
block2_mpi.libs/libgomp-a34b3233.so.1.0.0
block2_mpi.libs/libmkl_avx512.so.1
block2_mpi.libs/libevent_pthreads-2-f422e699.1.so.7.0.1
block2_mpi.libs/libpmix-baa9057b.so.2.13.3
block2_mpi.libs/libmkl_gnu_thread-76126a9d.so.1
block2_mpi.libs/libmkl_intel_lp64-eeafede9.so.1
block2_mpi-0.5.3.dist-info/top_level.txt
block2_mpi-0.5.3.dist-info/RECORD
block2_mpi-0.5.3.dist-info/METADATA
block2_mpi-0.5.3.dist-info/WHEEL
block2_mpi-0.5.3.dist-info/LICENSE
