Metadata-Version: 2.1
Name: block2-mpi
Version: 0.5.3
Summary: An efficient MPO implementation of DMRG for quantum chemistry.
Home-page: https://github.com/block-hczhai/block2-preview
Author: Huanchen Zhai, Henrik R. Larsson, Seunghoon Lee, and Zhi-Hao Cui
Author-email: hczhai.ok@gmail.com
License: LICENSE
License-File: LICENSE
Requires-Dist: mkl==2021.4
Requires-Dist: mkl-include
Requires-Dist: intel-openmp
Requires-Dist: numpy
Requires-Dist: cmake>=3.19
Requires-Dist: scipy
Requires-Dist: psutil
Requires-Dist: pybind11!=2.10.3,!=2.10.4,!=2.11.0,!=2.11.1
